{
	"info": {
		"_postman_id": "0f9701fc-dd91-4434-8e8a-3cb57ef39494",
		"name": "ToDo",
		"schema": "https://schema.getpostman.com/json/collection/v2.1.0/collection.json"
	},
	"item": [
		{
			"name": "register user",
			"protocolProfileBehavior": {
				"disabledSystemHeaders": {
					"accept-encoding": true
				}
			},
			"request": {
				"method": "POST",
				"header": [
					{
						"key": "Content-Type",
						"value": "application/json",
						"type": "text",
						"disabled": true
					}
				],
				"body": {
					"mode": "raw",
					"raw": "{\n    \"name\": \"Petro\",\n    \"surname\": \"Zaburko\",\n    \"email\": \"gigabyte_tech@ukr.net\",\n    \"password\": \"password\"\n}",
					"options": {
						"raw": {
							"language": "json"
						}
					}
				},
				"url": {
					"raw": "https://zaburko.softwars.com.ua/api/v1/register",
					"protocol": "https",
					"host": [
						"zaburko",
						"softwars",
						"com",
						"ua"
					],
					"path": [
						"api",
						"v1",
						"register"
					]
				}
			},
			"response": []
		},
		{
			"name": "login user",
			"protocolProfileBehavior": {
				"disabledSystemHeaders": {
					"accept-encoding": true
				}
			},
			"request": {
				"method": "POST",
				"header": [],
				"body": {
					"mode": "raw",
					"raw": "{\n    \"email\": \"gigabyte_tech@ukr.net\",\n    \"password\": \"password\"\n}",
					"options": {
						"raw": {
							"language": "json"
						}
					}
				},
				"url": {
					"raw": "https://zaburko.softwars.com.ua/api/v1/login",
					"protocol": "https",
					"host": [
						"zaburko",
						"softwars",
						"com",
						"ua"
					],
					"path": [
						"api",
						"v1",
						"login"
					]
				}
			},
			"response": []
		},
		{
			"name": "logout user",
			"protocolProfileBehavior": {
				"disabledSystemHeaders": {
					"accept-encoding": true
				}
			},
			"request": {
				"auth": {
					"type": "bearer",
					"bearer": [
						{
							"key": "token",
							"value": "10|fLBTkTJnQQG2pZczQ61x7x8B2EQ8A04BJPFBS6H5",
							"type": "string"
						}
					]
				},
				"method": "POST",
				"header": [],
				"url": {
					"raw": "https://zaburko.softwars.com.ua/api/v1/logout",
					"protocol": "https",
					"host": [
						"zaburko",
						"softwars",
						"com",
						"ua"
					],
					"path": [
						"api",
						"v1",
						"logout"
					]
				}
			},
			"response": []
		},
		{
			"name": "all tasks",
			"request": {
				"auth": {
					"type": "bearer",
					"bearer": [
						{
							"key": "token",
							"value": "10|fLBTkTJnQQG2pZczQ61x7x8B2EQ8A04BJPFBS6H5",
							"type": "string"
						}
					]
				},
				"method": "GET",
				"header": [],
				"url": {
					"raw": "https://zaburko.softwars.com.ua/api/v1/tasks",
					"protocol": "https",
					"host": [
						"zaburko",
						"softwars",
						"com",
						"ua"
					],
					"path": [
						"api",
						"v1",
						"tasks"
					]
				}
			},
			"response": []
		},
		{
			"name": "one task",
			"request": {
				"auth": {
					"type": "bearer",
					"bearer": [
						{
							"key": "token",
							"value": "10|fLBTkTJnQQG2pZczQ61x7x8B2EQ8A04BJPFBS6H5",
							"type": "string"
						}
					]
				},
				"method": "GET",
				"header": [],
				"url": {
					"raw": "https://zaburko.softwars.com.ua/api/v1/tasks/1",
					"protocol": "https",
					"host": [
						"zaburko",
						"softwars",
						"com",
						"ua"
					],
					"path": [
						"api",
						"v1",
						"tasks",
						"1"
					]
				}
			},
			"response": []
		},
		{
			"name": "create task",
			"protocolProfileBehavior": {
				"disabledSystemHeaders": {
					"accept-encoding": true
				}
			},
			"request": {
				"auth": {
					"type": "bearer",
					"bearer": [
						{
							"key": "token",
							"value": "10|fLBTkTJnQQG2pZczQ61x7x8B2EQ8A04BJPFBS6H5",
							"type": "string"
						}
					]
				},
				"method": "POST",
				"header": [],
				"body": {
					"mode": "raw",
					"raw": "{\n    \"title\": \"test\",\n    \"description\": \"test description\",\n    \"category_id\": 1,\n    \"importance\": 1,\n    \"user_id\": 1,\n    \"status\": 1\n}",
					"options": {
						"raw": {
							"language": "json"
						}
					}
				},
				"url": {
					"raw": "https://zaburko.softwars.com.ua/api/v1/tasks",
					"protocol": "https",
					"host": [
						"zaburko",
						"softwars",
						"com",
						"ua"
					],
					"path": [
						"api",
						"v1",
						"tasks"
					]
				}
			},
			"response": []
		},
		{
			"name": "update task",
			"protocolProfileBehavior": {
				"disabledSystemHeaders": {
					"content-type": true
				}
			},
			"request": {
				"auth": {
					"type": "bearer",
					"bearer": [
						{
							"key": "token",
							"value": "10|fLBTkTJnQQG2pZczQ61x7x8B2EQ8A04BJPFBS6H5",
							"type": "string"
						}
					]
				},
				"method": "PATCH",
				"header": [
					{
						"key": "Content-Type",
						"value": "application/json",
						"type": "text"
					}
				],
				"body": {
					"mode": "raw",
					"raw": "{\n    \"title\": \"test\",\n    \"description\": \"test description_test\"\n}",
					"options": {
						"raw": {
							"language": "json"
						}
					}
				},
				"url": {
					"raw": "https://zaburko.softwars.com.ua/api/v1/tasks/200",
					"protocol": "https",
					"host": [
						"zaburko",
						"softwars",
						"com",
						"ua"
					],
					"path": [
						"api",
						"v1",
						"tasks",
						"200"
					]
				}
			},
			"response": []
		},
		{
			"name": "change task status",
			"protocolProfileBehavior": {
				"disabledSystemHeaders": {
					"content-type": true
				}
			},
			"request": {
				"auth": {
					"type": "bearer",
					"bearer": [
						{
							"key": "token",
							"value": "10|fLBTkTJnQQG2pZczQ61x7x8B2EQ8A04BJPFBS6H5",
							"type": "string"
						}
					]
				},
				"method": "PATCH",
				"header": [],
				"body": {
					"mode": "urlencoded",
					"urlencoded": [],
					"options": {
						"raw": {
							"language": "json"
						}
					}
				},
				"url": {
					"raw": "https://zaburko.softwars.com.ua/api/v1/tasks/200/status",
					"protocol": "https",
					"host": [
						"zaburko",
						"softwars",
						"com",
						"ua"
					],
					"path": [
						"api",
						"v1",
						"tasks",
						"200",
						"status"
					]
				}
			},
			"response": []
		},
		{
			"name": "delete task",
			"protocolProfileBehavior": {
				"disabledSystemHeaders": {
					"content-type": true
				}
			},
			"request": {
				"auth": {
					"type": "bearer",
					"bearer": [
						{
							"key": "token",
							"value": "10|fLBTkTJnQQG2pZczQ61x7x8B2EQ8A04BJPFBS6H5",
							"type": "string"
						}
					]
				},
				"method": "DELETE",
				"header": [],
				"body": {
					"mode": "formdata",
					"formdata": [],
					"options": {
						"raw": {
							"language": "json"
						}
					}
				},
				"url": {
					"raw": "https://zaburko.softwars.com.ua/api/v1/tasks/200",
					"protocol": "https",
					"host": [
						"zaburko",
						"softwars",
						"com",
						"ua"
					],
					"path": [
						"api",
						"v1",
						"tasks",
						"200"
					]
				}
			},
			"response": []
		}
	]
}